Metadata-Version: 2.1
Name: streamingcli
Version: 2.0.1
Summary: Streaming platform CLI
Home-page: https://github.com/getindata/streaming-cli
Author: GetInData
Author-email: office@getindata.com
Classifier: Programming Language :: Python :: 3.8
Classifier: Operating System :: OS Independent
Requires-Python: >=3.8
Provides-Extra: tests
License-File: LICENSE
